{
    "resultCode": 0, 
    "resultMsg": "success", 
    "data": {
        "list": [
            {
		"id": "1168786315902201811",
		"name": "长安福特冬季特惠.....",
		"image": "https://ss1.bdstatic.com/5aAHeD3nKgcUp2HgoI7O1ygwehsv/media/ch1000/jpg/%E9%80%9A%E6%A0%8F38pc.jpg",
		"image1": "https://ss1.bdstatic.com/5aAHeD3nKgcUp2HgoI7O1ygwehsv/media/ch1000/jpg/%E9%80%9A%E6%A0%8F38pc.jpg",
		"type": 1,
                "activityScope": "1232312",
                "activityScopeName": "广州",
                "readTotal": 11,
                "commentTotal": 1,
                "publishTime": "2018-03-10 16:48:00",
                 "subhead": "7折优惠"
            },
            {
		"id": "1168786315902201822",
		"name": "长安福特冬季特惠.....",
		"image": "https://ss1.bdstatic.com/5aAHeD3nKgcUp2HgoI7O1ygwehsv/media/ch1000/jpg/%E9%80%9A%E6%A0%8F38pc.jpg",
		"image1": "https://ss1.bdstatic.com/5aAHeD3nKgcUp2HgoI7O1ygwehsv/media/ch1000/jpg/%E9%80%9A%E6%A0%8F38pc.jpg",
		"type": 1,
                "activityScope": "1232312",
                "activityScopeName": "广州",
                "readTotal": 11,
                "commentTotal": 1,
                "publishTime": "2018-03-10 16:48:00",
                 "subhead": "7折优惠"
            }
        ], 
        "pageNum": 1, 
        "pageSize": 10, 
        "pages": 1, 
        "total": 2
    }
}